MANIFEST.in
setup.py
recast_control_center_prototype.egg-info/PKG-INFO
recast_control_center_prototype.egg-info/SOURCES.txt
recast_control_center_prototype.egg-info/dependency_links.txt
recast_control_center_prototype.egg-info/entry_points.txt
recast_control_center_prototype.egg-info/not-zip-safe
recast_control_center_prototype.egg-info/requires.txt
recast_control_center_prototype.egg-info/top_level.txt
recastcontrolcenter/__init__.py
recastcontrolcenter/backendtasks.py
recastcontrolcenter/recast_interface_blueprint.py
recastcontrolcenter/recastconfig.py
recastcontrolcenter/server.py
recastcontrolcenter/servercli.py
recastcontrolcenter/socketapp.py
recastcontrolcenter/admin/__init__.py
recastcontrolcenter/admin/default_config.py
recastcontrolcenter/admin/recastadmin.py
recastcontrolcenter/recast_interface_templates/recast_all_requests.html
recastcontrolcenter/recast_interface_templates/recast_catalogue.html
recastcontrolcenter/recast_interface_templates/recast_request.html
recastcontrolcenter/resources/backendconfig.yml
recastcontrolcenter/resources/config.yaml
recastcontrolcenter/static/myvega.json
recastcontrolcenter/static/overview.json
recastcontrolcenter/static/vegavistemplate.json
recastcontrolcenter/static/vegavistemplate1d.json
recastcontrolcenter/static/vegavistemplate2d.json
recastcontrolcenter/static/FlexiJsonEditor/LICENSE
recastcontrolcenter/static/FlexiJsonEditor/README.md
recastcontrolcenter/static/FlexiJsonEditor/jquery.jsoneditor.js
recastcontrolcenter/static/FlexiJsonEditor/jquery.jsoneditor.min.js
recastcontrolcenter/static/FlexiJsonEditor/jquery.min.js
recastcontrolcenter/static/FlexiJsonEditor/json2.js
recastcontrolcenter/static/FlexiJsonEditor/jsoneditor.css
recastcontrolcenter/static/FlexiJsonEditor/jsoneditor.html
recastcontrolcenter/static/FlexiJsonEditor/jsoneditor.js
recastcontrolcenter/static/FlexiJsonEditor/logo-small.png
recastcontrolcenter/static/FlexiJsonEditor/logo.png
recastcontrolcenter/static/FlexiJsonEditor/logo.xcf
recastcontrolcenter/static/assets/recast.ico
recastcontrolcenter/static/bower_components/bootstrap/.bower.json
recastcontrolcenter/static/bower_components/bootstrap/CHANGELOG.md
recastcontrolcenter/static/bower_components/bootstrap/Gemfile
recastcontrolcenter/static/bower_components/bootstrap/Gemfile.lock
recastcontrolcenter/static/bower_components/bootstrap/Gruntfile.js
